Metadata-Version: 1.0
Name: bytexpy
Version: 0.2
Summary: Easy Graphics
Home-page: UNKNOWN
Author: UNKNOWN
Author-email: spgerghelp@gmail.com
License: UNKNOWN
Platform: UNKNOWN
